[
    {
        "id": "mqtt_in_temp",
        "type": "mqtt in",
        "z": "flow1",
        "name": "Temperature",
        "topic": "iot/home/temperature",
        "qos": "0",
        "datatype": "auto",
        "broker": "mqtt_broker",
        "x": 120,
        "y": 80,
        "wires": [["ui_gauge_temp"]]
    },
    {
        "id": "ui_gauge_temp",
        "type": "ui_gauge",
        "z": "flow1",
        "name": "Temp Gauge",
        "group": "home_tab",
        "order": 1,
        "width": 3,
        "height": 2,
        "gtype": "gage",
        "title": "Temp (°C)",
        "label": "°C",
        "format": "{{value}}",
        "min": 0,
        "max": 50,
        "colors": ["#00b500","#e6e600","#ca3838"],
        "x": 300,
        "y": 80,
        "wires": []
    },
    {
        "id": "mqtt_out_fan",
        "type": "mqtt out",
        "z": "flow1",
        "name": "Fan Control",
        "topic": "iot/home/fan",
        "qos": "0",
        "retain": "",
        "broker": "mqtt_broker",
        "x": 500,
        "y": 180,
        "wires": []
    },
    {
        "id": "ui_switch_fan",
        "type": "ui_switch",
        "z": "flow1",
        "name": "Fan Switch",
        "label": "Fan",
        "group": "control_tab",
        "order": 1,
        "width": 2,
        "height": 1,
        "passthru": true,
        "topic": "",
        "style": "",
        "onvalue": "ON",
        "onvalueType": "str",
        "offvalue": "OFF",
        "offvalueType": "str",
        "x": 320,
        "y": 180,
        "wires": [["mqtt_out_fan"]]
    },
    {
        "id": "mqtt_broker",
        "type": "mqtt-broker",
        "name": "Local MQTT",
        "broker": "192.168.1.100",
        "port": "1883",
        "clientid": "",
        "usetls": false,
        "compatmode": true,
        "keepalive": "60",
        "cleansession": true,
        "birthTopic": "",
        "birthQos": "0",
        "birthPayload": "",
        "closeTopic": "",
        "closePayload": "",
        "willTopic": "",
        "willQos": "0",
        "willPayload": ""
    }
]